AUTHORS
apiclient_pydantic/__init__.py
apiclient_pydantic/serializers.py
apiclient_pydantic/v1/__init__.py
apiclient_pydantic/v1/serializers.py
apiclient_pydantic/v1/utils.py
api_client_pydantic-3.1.0.dist-info/AUTHORS
api_client_pydantic-3.1.0.dist-info/LICENSE
api_client_pydantic-3.1.0.dist-info/METADATA
api_client_pydantic-3.1.0.dist-info/WHEEL
api_client_pydantic-3.1.0.dist-info/RECORD
