Metadata-Version: 2.1
Name: api-client-pydantic
Version: 3.1.0
Summary: API Client extension for validate and transform requests / responses using pydantic.
Home-page: https://github.com/mom1/api-client-pydantic
License: MIT
Keywords: api-client,api-client-extension
Author: MaxST
Author-email: mstolpasov@gmail.com
Requires-Python: >=3.9,<4
Classifier: Development Status :: 5 - Production/Stable
Classifier: Environment :: Web Environment
Classifier: Intended Audience :: Developers
Classifier: License :: OSI Approved :: MIT License
Classifier: Operating System :: OS Independent
Classifier: Programming Language :: Python
Classifier: Programming Language :: Python :: 3
Classifier: Programming Language :: Python :: 3.9
Classifier: Programming Language :: Python :: 3.10
Classifier: Programming Language :: Python :: 3.11
Classifier: Programming Language :: Python :: 3.12
Classifier: Programming Language :: Python :: 3.13
Classifier: Programming Language :: Python :: 3.8
Classifier: Topic :: Internet :: WWW/HTTP :: Dynamic Content
Requires-Dist: api-client (>1.2.1)
Requires-Dist: pydantic (>=2.10,<3.0)
Project-URL: Repository, https://github.com/mom1/api-client-pydantic
